moodle_tools/__init__.py
moodle_tools/analyze_results.py
moodle_tools/enums.py
moodle_tools/make_questions.py
moodle_tools/py.typed
moodle_tools/utils.py
moodle_tools/yaml_constructors.py
moodle_tools/questions/__init__.py
moodle_tools/questions/cloze.py
moodle_tools/questions/coderunner.py
moodle_tools/questions/coderunner_sql.py
moodle_tools/questions/coderunner_streaming.py
moodle_tools/questions/description.py
moodle_tools/questions/dragdrop_missing_words.py
moodle_tools/questions/drop_down.py
moodle_tools/questions/essay.py
moodle_tools/questions/factory.py
moodle_tools/questions/matching.py
moodle_tools/questions/missing_words.py
moodle_tools/questions/multiple_choice.py
moodle_tools/questions/multiple_response.py
moodle_tools/questions/multiple_true_false.py
moodle_tools/questions/numerical.py
moodle_tools/questions/ordering.py
moodle_tools/questions/question.py
moodle_tools/questions/shortanswer.py
moodle_tools/questions/true_false.py
moodle_tools/questions/templates/cloze.xml.j2
moodle_tools/questions/templates/coderunner.xml.j2
moodle_tools/questions/templates/description.xml.j2
moodle_tools/questions/templates/dragdrop_missing_words.xml.j2
moodle_tools/questions/templates/essay.xml.j2
moodle_tools/questions/templates/matching.xml.j2
moodle_tools/questions/templates/missing_words.xml.j2
moodle_tools/questions/templates/multiple_choice.xml.j2
moodle_tools/questions/templates/multiple_true_false.xml.j2
moodle_tools/questions/templates/numerical.xml.j2
moodle_tools/questions/templates/ordering.xml.j2
moodle_tools/questions/templates/question.xml.j2
moodle_tools/questions/templates/quiz.xml.j2
moodle_tools/questions/templates/shortanswer.xml.j2
moodle_tools/questions/templates/testlogic_ddl.py.j2
moodle_tools/questions/templates/testlogic_dql.py.j2
moodle_tools/questions/templates/testlogic_streaming.py.j2
moodle_tools/questions/templates/true_false.xml.j2
moodle_tools/questions/templates/ddl_check_tablecorrectness/10-name.sql.j2
moodle_tools-1.1.0.dist-info/METADATA
moodle_tools-1.1.0.dist-info/WHEEL
moodle_tools-1.1.0.dist-info/entry_points.txt
moodle_tools-1.1.0.dist-info/licenses/LICENSE
moodle_tools-1.1.0.dist-info/RECORD
