Metadata-Version: 2.4
Name: moodle-tools
Version: 1.1.0
Summary: A collection of tools to simplify working with Moodle quizzes.
Project-URL: Homepage, https://git.tu-berlin.de/dima/moodle-tools
Project-URL: Repository, https://git.tu-berlin.de/dima/moodle-tools
Project-URL: Documentation, https://dima.gitlab-pages.tu-berlin.de/moodle-tools
Project-URL: Bug Tracker, https://git.tu-berlin.de/dima/moodle-tools/-/issues
Author-email: Lennart Behme <lennart.behme@tu-berlin.de>, Gereon Dusella <gereon.dusella@tu-berlin.de>, Ricardo Ernesto Martinez Ramirez <r.martinez.ramirez@tu-berlin.de>, Viktor Rosenfeld <viktor.rosenfeld@tu-berlin.de>
Maintainer-email: The ISDA Team <isda@dima.tu-berlin.de>
License-Expression: Apache-2.0
License-File: LICENSE
Keywords: moodle,teaching
Classifier: License :: OSI Approved :: Apache Software License
Classifier: Operating System :: OS Independent
Classifier: Programming Language :: Python :: 3.11
Classifier: Programming Language :: Python :: 3.12
Classifier: Programming Language :: Python :: 3.13
Requires-Python: >=3.11
Requires-Dist: asteval~=1.0
Requires-Dist: jinja2~=3.1
Requires-Dist: loguru~=0.7.0
Requires-Dist: markdown~=3.4
Requires-Dist: pyyaml~=6.0
Provides-Extra: isda
Requires-Dist: duckdb~=1.2; extra == 'isda'
Requires-Dist: isda-streaming~=1.2; extra == 'isda'
Requires-Dist: sqlparse~=0.5.0; extra == 'isda'
